{
    "users": [
      {
        "id": 1,
        "name": "Francis",
        "lastname": "Jones"
      },
      {
        "id": 2,
        "name": "Steve",
        "lastname": "Chapman"
      },
      {
        "id": 4,
        "name": "Millie",
        "lastname": "Robson"
      },
      {
        "id": 5,
        "name": "Aranel",
        "lastname": "Kate"
      },
      {
        "id": 6,
        "name": "Reiby",
        "lastname": "Art"
      },
      {
        "id": 7,
        "name": "Tor",
        "lastname": "Son"
      }
    ]
  }

  